MANIFEST.in
README.txt
setup.py
docs/HISTORY.txt
src/zeam/__init__.py
src/zeam.form.base.egg-info/PKG-INFO
src/zeam.form.base.egg-info/SOURCES.txt
src/zeam.form.base.egg-info/dependency_links.txt
src/zeam.form.base.egg-info/namespace_packages.txt
src/zeam.form.base.egg-info/not-zip-safe
src/zeam.form.base.egg-info/requires.txt
src/zeam.form.base.egg-info/top_level.txt
src/zeam/form/__init__.py
src/zeam/form/base/__init__.py
src/zeam/form/base/actions.py
src/zeam/form/base/components.py
src/zeam/form/base/configure.zcml
src/zeam/form/base/datamanager.py
src/zeam/form/base/errors.py
src/zeam/form/base/fields.py
src/zeam/form/base/form.py
src/zeam/form/base/form_templates.py
src/zeam/form/base/ftesting.zcml
src/zeam/form/base/interfaces.py
src/zeam/form/base/markers.py
src/zeam/form/base/meta.py
src/zeam/form/base/sorters.py
src/zeam/form/base/testing.py
src/zeam/form/base/widgets.py
src/zeam/form/base/default_templates/formtemplate.cpt
src/zeam/form/base/ftests/__init__.py
src/zeam/form/base/ftests/test_form.py
src/zeam/form/base/ftests/forms/__init__.py
src/zeam/form/base/ftests/forms/extends.py
src/zeam/form/base/ftests/forms/inputform.py
src/zeam/form/base/ftests/forms/simpleform.py
src/zeam/form/base/ftests/widgets/__init__.py
src/zeam/form/base/ftests/widgets/widgetnorenderortemplate.py
src/zeam/form/base/ftests/widgets/widgetrender.py
src/zeam/form/base/ftests/widgets/widgettemplate.py
src/zeam/form/base/ftests/widgets/widgettemplate_templates/mywidget.cpt
src/zeam/form/base/i18n/zeam.form.base.pot
src/zeam/form/base/i18n/de/LC_MESSAGES/zeam.form.base.mo
src/zeam/form/base/i18n/de/LC_MESSAGES/zeam.form.base.po
src/zeam/form/base/i18n/en/LC_MESSAGES/zeam.form.base.mo
src/zeam/form/base/i18n/en/LC_MESSAGES/zeam.form.base.po
src/zeam/form/base/i18n/fr/LC_MESSAGES/zeam.form.base.mo
src/zeam/form/base/i18n/fr/LC_MESSAGES/zeam.form.base.po
src/zeam/form/base/i18n/nl/LC_MESSAGES/zeam.form.base.mo
src/zeam/form/base/i18n/nl/LC_MESSAGES/zeam.form.base.po
src/zeam/form/base/tests/__init__.py
src/zeam/form/base/tests/actions.txt
src/zeam/form/base/tests/components.txt
src/zeam/form/base/tests/fields.txt
src/zeam/form/base/tests/forms.txt
src/zeam/form/base/tests/test_doctest.py
src/zeam/form/base/tests/widgets.txt
src/zeam/form/base/widgets_templates/actionwidget.cpt
