Metadata-Version: 1.0
Name: zeam.form.base
Version: 1.2.2
Summary: Grok based form framework
Home-page: http://pypi.python.org/pypi/zeam.form.base
Author: Sylvain Viollon
Author-email: thefunny@gmail.com
License: BSD
Keywords: grok form framework
Platform: UNKNOWN
Classifier: Programming Language :: Python
Classifier: Topic :: Software Development :: Libraries :: Python Modules
